reppy/__init__.py
reppy/exceptions.py
reppy/robots.cpython-37m-darwin.so
reppy/ttl.py
reppy/util.py
reppy/cache/__init__.py
reppy/cache/policy.py
reppy-0.4.10.dist-info/METADATA
reppy-0.4.10.dist-info/RECORD
reppy-0.4.10.dist-info/WHEEL
reppy-0.4.10.dist-info/top_level.txt
