Metadata-Version: 2.1
Name: reppy
Version: 0.4.10
Summary: Replacement robots.txt Parser
Home-page: http://github.com/seomoz/reppy
Maintainer: Brandon Forehand
Maintainer-email: brandon@moz.com
License: MIT
Platform: Posix; MacOS X
Classifier: License :: OSI Approved :: MIT License
Classifier: Development Status :: 5 - Production/Stable
Classifier: Environment :: Web Environment
Classifier: Intended Audience :: Developers
Classifier: Topic :: Internet :: WWW/HTTP
Classifier: Programming Language :: Python :: 2.7
Classifier: Programming Language :: Python :: 3
Classifier: Programming Language :: Python :: 3.3
Classifier: Programming Language :: Python :: 3.4
Classifier: Programming Language :: Python :: 3.5
Classifier: Programming Language :: Python :: 3.6
Classifier: Programming Language :: Python :: 3.7
Requires-Dist: cachetools
Requires-Dist: python-dateutil (!=2.0,>=1.5)
Requires-Dist: requests
Requires-Dist: six
